asyncapi_codegen-0.5.0.data/scripts/asyncapi-codegen
asyncapicodegen/__init__.py
asyncapicodegen/_version.py
asyncapicodegen/cpp.py
asyncapicodegen/markdown_summary.py
asyncapicodegen/python_client.py
asyncapicodegen/python_summary.py
asyncapicodegen/specwrapper.py
asyncapicodegen/templates/cpp/__init__.py
asyncapicodegen/templates/cpp/broker.cpp.jinja2
asyncapicodegen/templates/cpp/broker.hpp.jinja2
asyncapicodegen/templates/cpp/file_prologue.jinja2
asyncapicodegen/templates/cpp/header.hpp.jinja2
asyncapicodegen/templates/cpp/ibrokerconnection.hpp.jinja2
asyncapicodegen/templates/cpp/message.hpp.jinja2
asyncapicodegen/templates/cpp/source.cpp.jinja2
asyncapicodegen/templates/cpp/type_helpers.jinja2
asyncapicodegen/templates/markdown/__init__.py
asyncapicodegen/templates/markdown/examples.md.jinja2
asyncapicodegen/templates/markdown/operation_list.md.jinja2
asyncapicodegen/templates/markdown/payload.md.jinja2
asyncapicodegen/templates/markdown/summary.md.jinja2
asyncapicodegen/templates/markdown/tags.md.jinja2
asyncapicodegen/templates/python/__init__.py
asyncapicodegen/templates/python/client.py.jinja2
asyncapicodegen/templates/python/setup.py.jinja2
asyncapicodegen/templates/python/summary.py.jinja2
asyncapi_codegen-0.5.0.dist-info/LICENSE
asyncapi_codegen-0.5.0.dist-info/METADATA
asyncapi_codegen-0.5.0.dist-info/WHEEL
asyncapi_codegen-0.5.0.dist-info/top_level.txt
asyncapi_codegen-0.5.0.dist-info/RECORD
