Metadata-Version: 2.1
Name: asyncapi-codegen
Version: 0.5.0
Summary: Generate C++ for an AsyncAPI Specification
Home-page: http://github.com/pearmaster/asyncapi-codgen
Author: Jacob Brunson
Author-email: pypi@jacobbrunson.com
License: GPLv2
Requires-Python: >=3.7
License-File: LICENSE
Requires-Dist: stringcase
Requires-Dist: json-schema-codegen (>=0.6.3)
Requires-Dist: pyyaml
Requires-Dist: ruamel.yaml
Requires-Dist: jacobs-jinja-too (>=0.0.4)
